[
  { "연번": 82797, "구": "용산구", "가맹점명칭": "마사" },
  { "연번": 83592, "구": "용산구", "가맹점명칭": "우육미엔이태원점" },
  { "연번": 83638, "구": "용산구", "가맹점명칭": "서울역철도떡볶이" },
  { "연번": 83729, "구": "용산구", "가맹점명칭": "은아네  맛집" },
  { "연번": 83962, "구": "용산구", "가맹점명칭": "고기반주" },
  { "연번": 84014, "구": "용산구", "가맹점명칭": "지금 보고싶다 한남동점" },
  { "연번": 84025, "구": "용산구", "가맹점명칭": "인생의 하이라이트" },
  { "연번": 84030, "구": "용산구", "가맹점명칭": "길섶" },
  { "연번": 84339, "구": "용산구", "가맹점명칭": "횡성한우목장" },
  { "연번": 84366, "구": "용산구", "가맹점명칭": "스탠다드원다이너" },
  { "연번": 84518, "구": "용산구", "가맹점명칭": "전주삼계탕" },
  { "연번": 84726, "구": "용산구", "가맹점명칭": "오썸델리" },
  { "연번": 85412, "구": "용산구", "가맹점명칭": "정가네석쇠불고기" },
  { "연번": 85824, "구": "용산구", "가맹점명칭": "선명구이가" },
  { "연번": 85955, "구": "용산구", "가맹점명칭": "주식회사 웰링턴서울" },
  { "연번": 86326, "구": "용산구", "가맹점명칭": "용문갈비" }
]
